{
  "node": {
    "7f7459ae977364c7fc13c469b86cbe54c16c0121f9": {
      "workers": {
        "app/(main)/dashboard/page": {
          "moduleId": "[project]/.next-internal/server/app/(main)/dashboard/page/actions.js { ACTIONS_MODULE0 => \"[project]/node_modules/@clerk/nextjs/dist/esm/app-router/server-actions.js [app-rsc] (ecmascript)\", ACTIONS_MODULE1 => \"[project]/node_modules/@clerk/nextjs/dist/esm/app-router/keyless-actions.js [app-rsc] (ecmascript)\", ACTIONS_MODULE2 => \"[project]/actions/dashboard.js [app-rsc] (ecmascript)\", ACTIONS_MODULE3 => \"[project]/actions/user.js [app-rsc] (ecmascript)\" } [app-rsc] (server actions loader, ecmascript)",
          "async": false
        }
      },
      "layer": {
        "app/(main)/dashboard/page": "action-browser"
      }
    },
    "7fca6e3ca248ccf59f4e36da2a70dc24b0233b7271": {
      "workers": {
        "app/(main)/dashboard/page": {
          "moduleId": "[project]/.next-internal/server/app/(main)/dashboard/page/actions.js { ACTIONS_MODULE0 => \"[project]/node_modules/@clerk/nextjs/dist/esm/app-router/server-actions.js [app-rsc] (ecmascript)\", ACTIONS_MODULE1 => \"[project]/node_modules/@clerk/nextjs/dist/esm/app-router/keyless-actions.js [app-rsc] (ecmascript)\", ACTIONS_MODULE2 => \"[project]/actions/dashboard.js [app-rsc] (ecmascript)\", ACTIONS_MODULE3 => \"[project]/actions/user.js [app-rsc] (ecmascript)\" } [app-rsc] (server actions loader, ecmascript)",
          "async": false
        }
      },
      "layer": {
        "app/(main)/dashboard/page": "action-browser"
      }
    },
    "7f0366068fcd97729616feeb57215a7003bc0f01dc": {
      "workers": {
        "app/(main)/dashboard/page": {
          "moduleId": "[project]/.next-internal/server/app/(main)/dashboard/page/actions.js { ACTIONS_MODULE0 => \"[project]/node_modules/@clerk/nextjs/dist/esm/app-router/server-actions.js [app-rsc] (ecmascript)\", ACTIONS_MODULE1 => \"[project]/node_modules/@clerk/nextjs/dist/esm/app-router/keyless-actions.js [app-rsc] (ecmascript)\", ACTIONS_MODULE2 => \"[project]/actions/dashboard.js [app-rsc] (ecmascript)\", ACTIONS_MODULE3 => \"[project]/actions/user.js [app-rsc] (ecmascript)\" } [app-rsc] (server actions loader, ecmascript)",
          "async": false
        }
      },
      "layer": {
        "app/(main)/dashboard/page": "action-browser"
      }
    },
    "0054ed17f7d31afaaadf373f176b6e6e2b22c208e5": {
      "workers": {
        "app/(main)/dashboard/page": {
          "moduleId": "[project]/.next-internal/server/app/(main)/dashboard/page/actions.js { ACTIONS_MODULE0 => \"[project]/node_modules/@clerk/nextjs/dist/esm/app-router/server-actions.js [app-rsc] (ecmascript)\", ACTIONS_MODULE1 => \"[project]/node_modules/@clerk/nextjs/dist/esm/app-router/keyless-actions.js [app-rsc] (ecmascript)\", ACTIONS_MODULE2 => \"[project]/actions/dashboard.js [app-rsc] (ecmascript)\", ACTIONS_MODULE3 => \"[project]/actions/user.js [app-rsc] (ecmascript)\" } [app-rsc] (server actions loader, ecmascript)",
          "async": false
        }
      },
      "layer": {
        "app/(main)/dashboard/page": "rsc"
      }
    },
    "7f5a5165cc090bda08b0e56c0195aa29854e964124": {
      "workers": {
        "app/(main)/dashboard/page": {
          "moduleId": "[project]/.next-internal/server/app/(main)/dashboard/page/actions.js { ACTIONS_MODULE0 => \"[project]/node_modules/@clerk/nextjs/dist/esm/app-router/server-actions.js [app-rsc] (ecmascript)\", ACTIONS_MODULE1 => \"[project]/node_modules/@clerk/nextjs/dist/esm/app-router/keyless-actions.js [app-rsc] (ecmascript)\", ACTIONS_MODULE2 => \"[project]/actions/dashboard.js [app-rsc] (ecmascript)\", ACTIONS_MODULE3 => \"[project]/actions/user.js [app-rsc] (ecmascript)\" } [app-rsc] (server actions loader, ecmascript)",
          "async": false
        }
      },
      "layer": {
        "app/(main)/dashboard/page": "rsc"
      }
    },
    "009e5a667237a0bf606b95e18b62f4c60b9c5d9ff8": {
      "workers": {
        "app/(main)/dashboard/page": {
          "moduleId": "[project]/.next-internal/server/app/(main)/dashboard/page/actions.js { ACTIONS_MODULE0 => \"[project]/node_modules/@clerk/nextjs/dist/esm/app-router/server-actions.js [app-rsc] (ecmascript)\", ACTIONS_MODULE1 => \"[project]/node_modules/@clerk/nextjs/dist/esm/app-router/keyless-actions.js [app-rsc] (ecmascript)\", ACTIONS_MODULE2 => \"[project]/actions/dashboard.js [app-rsc] (ecmascript)\", ACTIONS_MODULE3 => \"[project]/actions/user.js [app-rsc] (ecmascript)\" } [app-rsc] (server actions loader, ecmascript)",
          "async": false
        }
      },
      "layer": {
        "app/(main)/dashboard/page": "rsc"
      }
    },
    "40274f0e8d34cca2387fd9037c5ede12052ff8c575": {
      "workers": {
        "app/(main)/dashboard/page": {
          "moduleId": "[project]/.next-internal/server/app/(main)/dashboard/page/actions.js { ACTIONS_MODULE0 => \"[project]/node_modules/@clerk/nextjs/dist/esm/app-router/server-actions.js [app-rsc] (ecmascript)\", ACTIONS_MODULE1 => \"[project]/node_modules/@clerk/nextjs/dist/esm/app-router/keyless-actions.js [app-rsc] (ecmascript)\", ACTIONS_MODULE2 => \"[project]/actions/dashboard.js [app-rsc] (ecmascript)\", ACTIONS_MODULE3 => \"[project]/actions/user.js [app-rsc] (ecmascript)\" } [app-rsc] (server actions loader, ecmascript)",
          "async": false
        }
      },
      "layer": {
        "app/(main)/dashboard/page": "rsc"
      }
    }
  },
  "edge": {}
}